README.md
setup.py
bin/mtail
mtail/__init__.py
mtail/mtail.py
mtail.egg-info/PKG-INFO
mtail.egg-info/SOURCES.txt
mtail.egg-info/dependency_links.txt
mtail.egg-info/not-zip-safe
mtail.egg-info/top_level.txt