Metadata-Version: 1.0
Name: mtail
Version: 0.2
Summary: tails all log files in current directory
Home-page: https://github.com/set808/mtail
Author: Spencer Taylor
Author-email: spencertaylor808@gmail.com
License: MIT
Platform: UNKNOWN
